al_utils/__init__.py
al_utils/_res.py
al_utils/alru.py
al_utils/async_util.py
al_utils/console.py
al_utils/filter.py
al_utils/logger.py
al_utils/meta.py
al_utils/singleton.py
al_utils_almirai-0.1.0.dist-info/LICENSE
al_utils_almirai-0.1.0.dist-info/METADATA
al_utils_almirai-0.1.0.dist-info/WHEEL
al_utils_almirai-0.1.0.dist-info/top_level.txt
al_utils_almirai-0.1.0.dist-info/RECORD
