Metadata-Version: 2.1
Name: al-utils-almirai
Version: 0.1.0
Summary: Python common basic utilities for almirai projects.
Home-page: https://github.com/AlMiraiABC/py-common-utils.git
Author: AlMirai
Author-email: live.almirai@outlook.com
Project-URL: Bug Tracker, https://github.com/AlMiraiABC/py-common-utils/issues
Classifier: Programming Language :: Python :: 3
Classifier: License :: OSI Approved :: MIT License
Classifier: Operating System :: OS Independent
Requires-Python: >=3.6
License-File: LICENSE
